<?xml version="1.0" encoding="UTF-8"?>
<objects serializationModel="Studio.02.00.00">
	<object class="AudioFile" id="{01b99be3-ed05-4c03-ac6c-65ddf3213d5c}">
		<property name="assetPath">
			<value>VOX/lionheart_vox_generalhogg_hurt_light_v3.wav</value>
		</property>
		<property name="isStreaming">
			<value>true</value>
		</property>
		<property name="frequencyInKHz">
			<value>44.0999985</value>
		</property>
		<property name="channelCount">
			<value>1</value>
		</property>
		<property name="length">
			<value>0.27278911564625852</value>
		</property>
		<relationship name="masterAssetFolder">
			<destination>{26a7d39c-59b2-4e2e-90ea-52533bc18136}</destination>
		</relationship>
	</object>
</objects>
